vfit/app.py
vfit/core.py
vfit/util.py
vfit-2.1.0.dist-info/entry_points.txt
vfit-2.1.0.dist-info/LICENSE.txt
vfit-2.1.0.dist-info/WHEEL
vfit-2.1.0.dist-info/METADATA
vfit-2.1.0.dist-info/RECORD
